wsgidav/__init__.py
wsgidav/dav_error.py
wsgidav/dav_provider.py
wsgidav/default_conf.py
wsgidav/error_printer.py
wsgidav/fs_dav_provider.py
wsgidav/http_authenticator.py
wsgidav/request_resolver.py
wsgidav/request_server.py
wsgidav/rw_lock.py
wsgidav/stream_tools.py
wsgidav/util.py
wsgidav/wsgidav_app.py
wsgidav/xml_tools.py
wsgidav/dc/__init__.py
wsgidav/dc/base_dc.py
wsgidav/dc/nt_dc.py
wsgidav/dc/pam_dc.py
wsgidav/dc/simple_dc.py
wsgidav/dir_browser/__init__.py
wsgidav/dir_browser/_dir_browser.py
wsgidav/dir_browser/htdocs/favicon.ico
wsgidav/dir_browser/htdocs/logo.png
wsgidav/dir_browser/htdocs/script.js
wsgidav/dir_browser/htdocs/style.css
wsgidav/dir_browser/htdocs/template.html
wsgidav/lock_man/__init__.py
wsgidav/lock_man/lock_manager.py
wsgidav/lock_man/lock_storage.py
wsgidav/lock_man/lock_storage_redis.py
wsgidav/mw/__init__.py
wsgidav/mw/base_mw.py
wsgidav/mw/cors.py
wsgidav/mw/debug_filter.py
wsgidav/prop_man/__init__.py
wsgidav/prop_man/couch_property_manager.py
wsgidav/prop_man/mongo_property_manager.py
wsgidav/prop_man/property_manager.py
wsgidav/samples/__init__.py
wsgidav/samples/dav_provider_tools.py
wsgidav/samples/hg_dav_provider.py
wsgidav/samples/mongo_dav_provider.py
wsgidav/samples/mysql_dav_provider.py
wsgidav/samples/virtual_dav_provider.py
wsgidav/server/__init__.py
wsgidav/server/ext_wsgiutils_server.py
wsgidav/server/run_reloading_server.py
wsgidav/server/server_cli.py
wsgidav/server/server_sample.py
WsgiDAV-4.3.3.dist-info/LICENSE
WsgiDAV-4.3.3.dist-info/METADATA
WsgiDAV-4.3.3.dist-info/WHEEL
WsgiDAV-4.3.3.dist-info/entry_points.txt
WsgiDAV-4.3.3.dist-info/top_level.txt
WsgiDAV-4.3.3.dist-info/RECORD
