Metadata-Version: 2.1
Name: WsgiDAV
Version: 4.3.3
Summary: Generic and extendable WebDAV server based on WSGI
Home-page: https://github.com/mar10/wsgidav
Author: Martin Wendt
Author-email: wsgidav@wwwendt.de
Maintainer: Martin Wendt
Maintainer-email: wsgidav@wwwendt.de
License: MIT
Project-URL: Bug Tracker, https://github.com/mar10/wsgidav/issues
Project-URL: Source Code, https://github.com/mar10/wsgidav
Project-URL: Documentation, https://wsgidav.readthedocs.io
Project-URL: Download, https://github.com/mar10/wsgidav/releases/latest
Project-URL: Discussions, https://github.com/mar10/wsgidav/discussions
Keywords: web,wsgi,webdav,application,server
Classifier: Development Status :: 5 - Production/Stable
Classifier: Environment :: Console
Classifier: Intended Audience :: Developers
Classifier: Intended Audience :: Information Technology
Classifier: Intended Audience :: System Administrators
Classifier: License :: OSI Approved :: MIT License
Classifier: Operating System :: OS Independent
Classifier: Programming Language :: Python
Classifier: Programming Language :: Python :: 3
Classifier: Programming Language :: Python :: 3 :: Only
Classifier: Programming Language :: Python :: 3.8
Classifier: Programming Language :: Python :: 3.9
Classifier: Programming Language :: Python :: 3.10
Classifier: Programming Language :: Python :: 3.11
Classifier: Programming Language :: Python :: 3.12
Classifier: Topic :: Internet :: WWW/HTTP
Classifier: Topic :: Internet :: WWW/HTTP :: HTTP Servers
Classifier: Topic :: Internet :: WWW/HTTP :: Dynamic Content
Classifier: Topic :: Internet :: WWW/HTTP :: WSGI
Classifier: Topic :: Internet :: WWW/HTTP :: WSGI :: Application
Classifier: Topic :: Internet :: WWW/HTTP :: WSGI :: Server
Classifier: Topic :: Software Development :: Libraries :: Python Modules
License-File: LICENSE
Requires-Dist: defusedxml
Requires-Dist: Jinja2
Requires-Dist: json5
Requires-Dist: PyYAML
Provides-Extra: pam
Requires-Dist: python-pam; extra == "pam"
